{
    "id": "ilqa2zkhenmjr5db5w6tpuidf3vio4lq",
    "title": "Scale and Rotation Invariant Detection of Singular Patterns in Vector Flow Fields",
    "info": {
        "author": [
            "Wei Liu, Florida Institute of Technology"
        ],
        "published": "Sept. 13, 2010",
        "recorded": "August 2010",
        "category": [
            "Top->Computer Science->Pattern Recognition"
        ]
    },
    "url": "http://videolectures.net/ssspr2010_liu_srv/",
    "segmentation": [
        [
            "I'm new and I'm from Florida Institute of Technology and see this small label an I'm presenting my work with Ron Rivera.",
            "And retention environment interaction.",
            "Similar patterns in flow fields.",
            "Not yet, I will.",
            "Input is currently close an we trying to rotation and sinks or things that is interesting in many applications.",
            "For example in the manual system we want to detect things like hurricanes, huge pretentions and sudden changes.",
            "Emergence of the cloud or spattering of the cloud.",
            "An another example.",
            "Fingerprint.",
            "Had similar patterns in your fingerprint, but.",
            "We learn the methods that is very similar to serve, but unlike SIP which is extensive study for magnaflow is quite new.",
            "The difficulty is that no patterns has different Sciences, even the scales and orientations.",
            "So our method is trying to impose the flow field using basic flow patterns and this small patterns are represented using complex polynomials, so it allows us to handle channel metric transformations like rotation and scaling.",
            "I algebra calculation which is more efficient?",
            "So like this, if we calculate within five or so singular energy that measures how similar.",
            "Flower Field is locally similar to our bench.",
            "Is similar patterns and then we have this energy or multiple still images an we find the local minimum maximums of the single language along this news so.",
            "Different sizes and after that we align the flow field by rotating them to our patients flow.",
            "As a subspace projection, so emotion online to find out intrinsic or intentions of low patterns.",
            "Interestingly, unlike images which may just have one or intention principle intention mclovins, then multiple ones.",
            "Hasn't symmetric nature news, so.",
            "We in this one we provided our source code and test test data.",
            "I guess if you're interested, be sure to check it out.",
            "And we also know some preliminary applications such as classification on the similar patterns, and we also try to manage separate similar patterns that is corrupted by background flows.",
            "So we hope that inspired many more applications.",
            "That's it."
        ]
    ],
    "summarization": {
        "clip_0": {
            "is_summarization_sample": true,
            "summarization_data": [
                {
                    "sent": "I'm new and I'm from Florida Institute of Technology and see this small label an I'm presenting my work with Ron Rivera.",
                    "label": 0
                },
                {
                    "sent": "And retention environment interaction.",
                    "label": 0
                },
                {
                    "sent": "Similar patterns in flow fields.",
                    "label": 1
                },
                {
                    "sent": "Not yet, I will.",
                    "label": 0
                },
                {
                    "sent": "Input is currently close an we trying to rotation and sinks or things that is interesting in many applications.",
                    "label": 0
                },
                {
                    "sent": "For example in the manual system we want to detect things like hurricanes, huge pretentions and sudden changes.",
                    "label": 0
                },
                {
                    "sent": "Emergence of the cloud or spattering of the cloud.",
                    "label": 0
                },
                {
                    "sent": "An another example.",
                    "label": 0
                },
                {
                    "sent": "Fingerprint.",
                    "label": 0
                },
                {
                    "sent": "Had similar patterns in your fingerprint, but.",
                    "label": 0
                },
                {
                    "sent": "We learn the methods that is very similar to serve, but unlike SIP which is extensive study for magnaflow is quite new.",
                    "label": 0
                },
                {
                    "sent": "The difficulty is that no patterns has different Sciences, even the scales and orientations.",
                    "label": 0
                },
                {
                    "sent": "So our method is trying to impose the flow field using basic flow patterns and this small patterns are represented using complex polynomials, so it allows us to handle channel metric transformations like rotation and scaling.",
                    "label": 1
                },
                {
                    "sent": "I algebra calculation which is more efficient?",
                    "label": 0
                },
                {
                    "sent": "So like this, if we calculate within five or so singular energy that measures how similar.",
                    "label": 0
                },
                {
                    "sent": "Flower Field is locally similar to our bench.",
                    "label": 0
                },
                {
                    "sent": "Is similar patterns and then we have this energy or multiple still images an we find the local minimum maximums of the single language along this news so.",
                    "label": 1
                },
                {
                    "sent": "Different sizes and after that we align the flow field by rotating them to our patients flow.",
                    "label": 0
                },
                {
                    "sent": "As a subspace projection, so emotion online to find out intrinsic or intentions of low patterns.",
                    "label": 0
                },
                {
                    "sent": "Interestingly, unlike images which may just have one or intention principle intention mclovins, then multiple ones.",
                    "label": 0
                },
                {
                    "sent": "Hasn't symmetric nature news, so.",
                    "label": 1
                },
                {
                    "sent": "We in this one we provided our source code and test test data.",
                    "label": 0
                },
                {
                    "sent": "I guess if you're interested, be sure to check it out.",
                    "label": 0
                },
                {
                    "sent": "And we also know some preliminary applications such as classification on the similar patterns, and we also try to manage separate similar patterns that is corrupted by background flows.",
                    "label": 0
                },
                {
                    "sent": "So we hope that inspired many more applications.",
                    "label": 0
                },
                {
                    "sent": "That's it.",
                    "label": 0
                }
            ]
        }
    }
}