{
    "id": "leiuoxycphsfubaihnjwd5rhrzea6qok",
    "title": "Sparse Canonical Correlation Analysis",
    "info": {
        "author": [
            "David R. Hardoon, London's Global University"
        ],
        "published": "Dec. 18, 2008",
        "recorded": "December 2008",
        "category": [
            "Top->Social Sciences->Economics->Econometrics"
        ]
    },
    "url": "http://videolectures.net/sip08_hardoon_scca/",
    "segmentation": [
        [
            "So."
        ],
        [
            "So, um.",
            "Analysis.",
            "Motivation of wine.",
            "So I should be practicing.",
            "We actually use local machine learning.",
            "Final formulation also discussed why?",
            "Opposite give me actual method."
        ],
        [
            "OK, so thank you.",
            "So just very very great review so already.",
            "Colonel."
        ],
        [
            "OK, so.",
            "So.",
            "We are trying to find a linear combination that maximizes correlation between 2:00.",
            "So.",
            "Here we have it in combination.",
            "Various.",
            "One approach we generally take and run them thinking of this to use the actually have things sometimes of XP with some very high complex label.",
            "Which.",
            "OK honey, we refer to this as the machine level.",
            "Space song.",
            "Colonel CCA again.",
            "If you think about.",
            "Two representations of documents in one language.",
            "English documents.",
            "Another language.",
            "French hated working in the workspace while staying with the documents.",
            "Now."
        ],
        [
            "So motivation."
        ],
        [
            "Why do you want to see it?"
        ],
        [
            "And more importantly."
        ],
        [
            "OK, so this is very much like."
        ],
        [
            "So."
        ],
        [
            "Enzyme production.",
            "Stop subscribe."
        ],
        [
            "Has already started mentioning bilingual documents in one language and you want to find a particular mapping document in another.",
            "And.",
            "So.",
            "Worse.",
            "Arrange documents talking about agriculture.",
            "Good representation in English.",
            "Contest.",
            "All the documents in French book about something."
        ],
        [
            "Unlock very cold this representation.",
            "As in.",
            "Rain.",
            "Conflicts within the image, but they do want to have something to say."
        ],
        [
            "Anne.",
            "Many other."
        ],
        [
            "So.",
            "I'm not possible nature of the problem.",
            "French documents and just.",
            "Asian.",
            "Notice.",
            "Yeah."
        ],
        [
            "Scaling.",
            "So."
        ],
        [
            "OK, so.",
            "Maximizing correlation between two vectors having viewed as minimizing.",
            "Pretty much.",
            "So we can replace off maximization problems."
        ],
        [
            "OK, so now imagine minimizing the article.",
            "We can minimize.",
            "Vectors and then."
        ],
        [
            "But again, we have a problem.",
            "Where?",
            "0.",
            "So.",
            "We replaced and again because the solution isn't regular scaling.",
            "Running fixing this link."
        ],
        [
            "We will see why.",
            "Triple solutions."
        ],
        [
            "So now we know that.",
            "So we're able to be dropped now."
        ],
        [
            "And now allows us to impose sparsity on main components using a bundle.",
            "The animal crime waves WI want to remain in Hamilton, right?",
            "So it knows him.",
            "K + 1.",
            "One way.",
            "Documents.",
            "When I say I have a particular.",
            "Stars.",
            "At the same time."
        ],
        [
            "So final.",
            "Where the?",
            "Fasting."
        ],
        [
            "So pick one."
        ],
        [
            "Approach.",
            "Well, that.",
            "In our particular problem, only interested in opposing spectrum because we work with documents.",
            "There wasn't really any meaning or the negative contribution for document, so we just say we got books to obviously consulted with respect to both of the spectrum and so we represent.",
            "0.",
            "Minus and details on.",
            "So very simple, but.",
            "And now we."
        ],
        [
            "Everything.",
            "So.",
            "When we take me to play together, we found it album minus is essentially when alchemize 0A buses.",
            "He mentioned the jacket.",
            "Minus 0.",
            "So this kind of.",
            "By zero.",
            "Allows us to have a way of indicating which components WI.",
            "Zero, don't worry.",
            "When album stores zero or greater.",
            "Mute.",
            "Bring it up.",
            "Mute.",
            "Because going back.",
            "Any pizza is 0.",
            "Remember.",
            "Ek OK so.",
            "This allows the blue one particular production.",
            "We almost stabilized the plate on the next project.",
            "Very nice.",
            "Solution 2.",
            "Primal"
        ],
        [
            "So.",
            "Is that?",
            "Think.",
            "Where we cannot.",
            "Maybe?",
            "OK, so let me go."
        ],
        [
            "So we have two problems.",
            "One is a English medical facility.",
            "2600 2000 now in Spanish."
        ],
        [
            "So.",
            "As I mentioned in two different cases.",
            "Training documents, given a new document.",
            "Find me.",
            "The head meant so you haven't listened to.",
            "Testing where in the passing said is my mic.",
            "Obviously it works well, is always going to be rank one.",
            "This is the index.",
            "Should explain.",
            "As mentioned yesterday."
        ],
        [
            "Trying automatic approach.",
            "About how I'm gonna go about how many words.",
            "So.",
            "Usually one."
        ],
        [
            "Ask."
        ],
        [
            "So."
        ],
        [
            "Mute.",
            "Now.",
            "So.",
            "We will send you value that essentially is a set of assets."
        ],
        [
            "Anyway."
        ],
        [
            "Is mean.",
            "English.",
            "We refresh.",
            "Is the number of words that generated.",
            "Anyway, the same number of words as in the original document in English.",
            "Yelp?",
            "French.",
            "English in any way similar."
        ],
        [
            "So.",
            "Ratio.",
            "As functional.",
            "Value.",
            "We have 2.5.",
            "We generate new bag of Word document.",
            "Document for particular query.",
            "An ideal selection.",
            "Write down the horizontal line when we're generating the exact number of words as well.",
            "Is not that far.",
            "Now obviously this query which so we do this for all the documents for French law."
        ],
        [
            "Average across.",
            "Automatic processing uses a space.",
            "Cambridge.",
            "Average.",
            "Same number.",
            "What was?",
            "Unknown spots approach.",
            "Getting massive we're happy with our processing.",
            "Hollywood.",
            "OK, so.",
            "We go back to Maine.",
            "One hour."
        ],
        [
            "So I don't apologize.",
            "So this is the French English schools discover header using 50 documents to train 250 for testing.",
            "The X axis is the number of projection from use.",
            "Point average.",
            "The error summary.",
            "So as we can see.",
            "Obviously there is increasing.",
            "And all.",
            "Most of the time.",
            "Sea is able to be spotted.",
            "Conversions.",
            "Here we use an increase another training document 200 test document.",
            "One of them."
        ],
        [
            "These two off for the 5th training with $50.",
            "This is the one I was using.",
            "OK, So what woman find that in this particular problem with 2007?",
            "Over 140 bucks.",
            "Which is interesting.",
            "So really I go back.",
            "Which.",
            "Now here, so this is the primal weights.",
            "And here's the deal work so.",
            "Directions.",
            "Projection.",
            "On top of that.",
            "24 documents OK."
        ],
        [
            "Fashion increase.",
            "The noise.",
            "So.",
            "How 100 documents with rating as 900 for testing.",
            "The blue line in this case is today, the red line is pretty much.",
            "Well."
        ],
        [
            "Honda Fit.",
            "Documents.",
            "So.",
            "OK, so.",
            "The conclusion so."
        ],
        [
            "We had a method which was.",
            "On one view.",
            "Images.",
            "Then you can.",
            "Then what's going on?",
            "Generally.",
            "Automatic.",
            "Anne.",
            "Exactly.",
            "How to set?",
            "We quote.",
            "Project.",
            "Projection.",
            "Maybe you put protection.",
            "Changes.",
            "Negative.",
            "How?"
        ],
        [
            "Population.",
            "The problem with.",
            "So far it's exactly algorithm.",
            "Posted in conditional situations.",
            "So in essence, I guess.",
            "Modulation of the last Sue is equivalent to simply say that when you're estimating the application is not standard.",
            "Problem here if you just add, just add.",
            "So.",
            "I have a question.",
            "Never ever go back."
        ],
        [
            "Old.",
            "In this case.",
            "Free.",
            "Basically as well that we may have.",
            "There is.",
            "The problem is a magician with certain pressure because of his pain, which is somewhere and well so.",
            "I'm not trying.",
            "One, and then you guys.",
            "Problem.",
            "Starting point.",
            "But I agree.",
            "Penis"
        ]
    ],
    "summarization": {
        "clip_0": {
            "is_summarization_sample": false,
            "summarization_data": [
                {
                    "sent": "So.",
                    "label": 0
                }
            ]
        },
        "clip_1": {
            "is_summarization_sample": true,
            "summarization_data": [
                {
                    "sent": "So, um.",
                    "label": 0
                },
                {
                    "sent": "Analysis.",
                    "label": 0
                },
                {
                    "sent": "Motivation of wine.",
                    "label": 0
                },
                {
                    "sent": "So I should be practicing.",
                    "label": 0
                },
                {
                    "sent": "We actually use local machine learning.",
                    "label": 1
                },
                {
                    "sent": "Final formulation also discussed why?",
                    "label": 0
                },
                {
                    "sent": "Opposite give me actual method.",
                    "label": 0
                }
            ]
        },
        "clip_2": {
            "is_summarization_sample": false,
            "summarization_data": [
                {
                    "sent": "OK, so thank you.",
                    "label": 0
                },
                {
                    "sent": "So just very very great review so already.",
                    "label": 0
                },
                {
                    "sent": "Colonel.",
                    "label": 0
                }
            ]
        },
        "clip_3": {
            "is_summarization_sample": true,
            "summarization_data": [
                {
                    "sent": "OK, so.",
                    "label": 0
                },
                {
                    "sent": "So.",
                    "label": 0
                },
                {
                    "sent": "We are trying to find a linear combination that maximizes correlation between 2:00.",
                    "label": 1
                },
                {
                    "sent": "So.",
                    "label": 0
                },
                {
                    "sent": "Here we have it in combination.",
                    "label": 0
                },
                {
                    "sent": "Various.",
                    "label": 0
                },
                {
                    "sent": "One approach we generally take and run them thinking of this to use the actually have things sometimes of XP with some very high complex label.",
                    "label": 0
                },
                {
                    "sent": "Which.",
                    "label": 0
                },
                {
                    "sent": "OK honey, we refer to this as the machine level.",
                    "label": 0
                },
                {
                    "sent": "Space song.",
                    "label": 0
                },
                {
                    "sent": "Colonel CCA again.",
                    "label": 0
                },
                {
                    "sent": "If you think about.",
                    "label": 0
                },
                {
                    "sent": "Two representations of documents in one language.",
                    "label": 0
                },
                {
                    "sent": "English documents.",
                    "label": 0
                },
                {
                    "sent": "Another language.",
                    "label": 0
                },
                {
                    "sent": "French hated working in the workspace while staying with the documents.",
                    "label": 0
                },
                {
                    "sent": "Now.",
                    "label": 0
                }
            ]
        },
        "clip_4": {
            "is_summarization_sample": false,
            "summarization_data": [
                {
                    "sent": "So motivation.",
                    "label": 0
                }
            ]
        },
        "clip_5": {
            "is_summarization_sample": false,
            "summarization_data": [
                {
                    "sent": "Why do you want to see it?",
                    "label": 0
                }
            ]
        },
        "clip_6": {
            "is_summarization_sample": false,
            "summarization_data": [
                {
                    "sent": "And more importantly.",
                    "label": 0
                }
            ]
        },
        "clip_7": {
            "is_summarization_sample": false,
            "summarization_data": [
                {
                    "sent": "OK, so this is very much like.",
                    "label": 0
                }
            ]
        },
        "clip_8": {
            "is_summarization_sample": false,
            "summarization_data": [
                {
                    "sent": "So.",
                    "label": 0
                }
            ]
        },
        "clip_9": {
            "is_summarization_sample": false,
            "summarization_data": [
                {
                    "sent": "Enzyme production.",
                    "label": 0
                },
                {
                    "sent": "Stop subscribe.",
                    "label": 0
                }
            ]
        },
        "clip_10": {
            "is_summarization_sample": false,
            "summarization_data": [
                {
                    "sent": "Has already started mentioning bilingual documents in one language and you want to find a particular mapping document in another.",
                    "label": 0
                },
                {
                    "sent": "And.",
                    "label": 0
                },
                {
                    "sent": "So.",
                    "label": 0
                },
                {
                    "sent": "Worse.",
                    "label": 0
                },
                {
                    "sent": "Arrange documents talking about agriculture.",
                    "label": 0
                },
                {
                    "sent": "Good representation in English.",
                    "label": 0
                },
                {
                    "sent": "Contest.",
                    "label": 0
                },
                {
                    "sent": "All the documents in French book about something.",
                    "label": 0
                }
            ]
        },
        "clip_11": {
            "is_summarization_sample": false,
            "summarization_data": [
                {
                    "sent": "Unlock very cold this representation.",
                    "label": 0
                },
                {
                    "sent": "As in.",
                    "label": 0
                },
                {
                    "sent": "Rain.",
                    "label": 0
                },
                {
                    "sent": "Conflicts within the image, but they do want to have something to say.",
                    "label": 0
                }
            ]
        },
        "clip_12": {
            "is_summarization_sample": false,
            "summarization_data": [
                {
                    "sent": "Anne.",
                    "label": 0
                },
                {
                    "sent": "Many other.",
                    "label": 0
                }
            ]
        },
        "clip_13": {
            "is_summarization_sample": false,
            "summarization_data": [
                {
                    "sent": "So.",
                    "label": 0
                },
                {
                    "sent": "I'm not possible nature of the problem.",
                    "label": 0
                },
                {
                    "sent": "French documents and just.",
                    "label": 0
                },
                {
                    "sent": "Asian.",
                    "label": 0
                },
                {
                    "sent": "Notice.",
                    "label": 0
                },
                {
                    "sent": "Yeah.",
                    "label": 0
                }
            ]
        },
        "clip_14": {
            "is_summarization_sample": false,
            "summarization_data": [
                {
                    "sent": "Scaling.",
                    "label": 0
                },
                {
                    "sent": "So.",
                    "label": 0
                }
            ]
        },
        "clip_15": {
            "is_summarization_sample": true,
            "summarization_data": [
                {
                    "sent": "OK, so.",
                    "label": 0
                },
                {
                    "sent": "Maximizing correlation between two vectors having viewed as minimizing.",
                    "label": 1
                },
                {
                    "sent": "Pretty much.",
                    "label": 0
                },
                {
                    "sent": "So we can replace off maximization problems.",
                    "label": 0
                }
            ]
        },
        "clip_16": {
            "is_summarization_sample": false,
            "summarization_data": [
                {
                    "sent": "OK, so now imagine minimizing the article.",
                    "label": 0
                },
                {
                    "sent": "We can minimize.",
                    "label": 0
                },
                {
                    "sent": "Vectors and then.",
                    "label": 0
                }
            ]
        },
        "clip_17": {
            "is_summarization_sample": false,
            "summarization_data": [
                {
                    "sent": "But again, we have a problem.",
                    "label": 0
                },
                {
                    "sent": "Where?",
                    "label": 0
                },
                {
                    "sent": "0.",
                    "label": 0
                },
                {
                    "sent": "So.",
                    "label": 0
                },
                {
                    "sent": "We replaced and again because the solution isn't regular scaling.",
                    "label": 0
                },
                {
                    "sent": "Running fixing this link.",
                    "label": 0
                }
            ]
        },
        "clip_18": {
            "is_summarization_sample": false,
            "summarization_data": [
                {
                    "sent": "We will see why.",
                    "label": 0
                },
                {
                    "sent": "Triple solutions.",
                    "label": 0
                }
            ]
        },
        "clip_19": {
            "is_summarization_sample": false,
            "summarization_data": [
                {
                    "sent": "So now we know that.",
                    "label": 0
                },
                {
                    "sent": "So we're able to be dropped now.",
                    "label": 0
                }
            ]
        },
        "clip_20": {
            "is_summarization_sample": false,
            "summarization_data": [
                {
                    "sent": "And now allows us to impose sparsity on main components using a bundle.",
                    "label": 0
                },
                {
                    "sent": "The animal crime waves WI want to remain in Hamilton, right?",
                    "label": 0
                },
                {
                    "sent": "So it knows him.",
                    "label": 0
                },
                {
                    "sent": "K + 1.",
                    "label": 0
                },
                {
                    "sent": "One way.",
                    "label": 0
                },
                {
                    "sent": "Documents.",
                    "label": 0
                },
                {
                    "sent": "When I say I have a particular.",
                    "label": 0
                },
                {
                    "sent": "Stars.",
                    "label": 0
                },
                {
                    "sent": "At the same time.",
                    "label": 0
                }
            ]
        },
        "clip_21": {
            "is_summarization_sample": false,
            "summarization_data": [
                {
                    "sent": "So final.",
                    "label": 0
                },
                {
                    "sent": "Where the?",
                    "label": 0
                },
                {
                    "sent": "Fasting.",
                    "label": 0
                }
            ]
        },
        "clip_22": {
            "is_summarization_sample": false,
            "summarization_data": [
                {
                    "sent": "So pick one.",
                    "label": 0
                }
            ]
        },
        "clip_23": {
            "is_summarization_sample": false,
            "summarization_data": [
                {
                    "sent": "Approach.",
                    "label": 0
                },
                {
                    "sent": "Well, that.",
                    "label": 0
                },
                {
                    "sent": "In our particular problem, only interested in opposing spectrum because we work with documents.",
                    "label": 0
                },
                {
                    "sent": "There wasn't really any meaning or the negative contribution for document, so we just say we got books to obviously consulted with respect to both of the spectrum and so we represent.",
                    "label": 0
                },
                {
                    "sent": "0.",
                    "label": 0
                },
                {
                    "sent": "Minus and details on.",
                    "label": 0
                },
                {
                    "sent": "So very simple, but.",
                    "label": 0
                },
                {
                    "sent": "And now we.",
                    "label": 0
                }
            ]
        },
        "clip_24": {
            "is_summarization_sample": false,
            "summarization_data": [
                {
                    "sent": "Everything.",
                    "label": 0
                },
                {
                    "sent": "So.",
                    "label": 0
                },
                {
                    "sent": "When we take me to play together, we found it album minus is essentially when alchemize 0A buses.",
                    "label": 0
                },
                {
                    "sent": "He mentioned the jacket.",
                    "label": 0
                },
                {
                    "sent": "Minus 0.",
                    "label": 0
                },
                {
                    "sent": "So this kind of.",
                    "label": 0
                },
                {
                    "sent": "By zero.",
                    "label": 0
                },
                {
                    "sent": "Allows us to have a way of indicating which components WI.",
                    "label": 0
                },
                {
                    "sent": "Zero, don't worry.",
                    "label": 0
                },
                {
                    "sent": "When album stores zero or greater.",
                    "label": 0
                },
                {
                    "sent": "Mute.",
                    "label": 0
                },
                {
                    "sent": "Bring it up.",
                    "label": 0
                },
                {
                    "sent": "Mute.",
                    "label": 0
                },
                {
                    "sent": "Because going back.",
                    "label": 0
                },
                {
                    "sent": "Any pizza is 0.",
                    "label": 0
                },
                {
                    "sent": "Remember.",
                    "label": 0
                },
                {
                    "sent": "Ek OK so.",
                    "label": 0
                },
                {
                    "sent": "This allows the blue one particular production.",
                    "label": 0
                },
                {
                    "sent": "We almost stabilized the plate on the next project.",
                    "label": 0
                },
                {
                    "sent": "Very nice.",
                    "label": 0
                },
                {
                    "sent": "Solution 2.",
                    "label": 0
                },
                {
                    "sent": "Primal",
                    "label": 0
                }
            ]
        },
        "clip_25": {
            "is_summarization_sample": false,
            "summarization_data": [
                {
                    "sent": "So.",
                    "label": 0
                },
                {
                    "sent": "Is that?",
                    "label": 0
                },
                {
                    "sent": "Think.",
                    "label": 0
                },
                {
                    "sent": "Where we cannot.",
                    "label": 0
                },
                {
                    "sent": "Maybe?",
                    "label": 0
                },
                {
                    "sent": "OK, so let me go.",
                    "label": 0
                }
            ]
        },
        "clip_26": {
            "is_summarization_sample": false,
            "summarization_data": [
                {
                    "sent": "So we have two problems.",
                    "label": 0
                },
                {
                    "sent": "One is a English medical facility.",
                    "label": 0
                },
                {
                    "sent": "2600 2000 now in Spanish.",
                    "label": 0
                }
            ]
        },
        "clip_27": {
            "is_summarization_sample": false,
            "summarization_data": [
                {
                    "sent": "So.",
                    "label": 0
                },
                {
                    "sent": "As I mentioned in two different cases.",
                    "label": 0
                },
                {
                    "sent": "Training documents, given a new document.",
                    "label": 0
                },
                {
                    "sent": "Find me.",
                    "label": 0
                },
                {
                    "sent": "The head meant so you haven't listened to.",
                    "label": 0
                },
                {
                    "sent": "Testing where in the passing said is my mic.",
                    "label": 0
                },
                {
                    "sent": "Obviously it works well, is always going to be rank one.",
                    "label": 0
                },
                {
                    "sent": "This is the index.",
                    "label": 0
                },
                {
                    "sent": "Should explain.",
                    "label": 0
                },
                {
                    "sent": "As mentioned yesterday.",
                    "label": 0
                }
            ]
        },
        "clip_28": {
            "is_summarization_sample": false,
            "summarization_data": [
                {
                    "sent": "Trying automatic approach.",
                    "label": 0
                },
                {
                    "sent": "About how I'm gonna go about how many words.",
                    "label": 0
                },
                {
                    "sent": "So.",
                    "label": 0
                },
                {
                    "sent": "Usually one.",
                    "label": 0
                }
            ]
        },
        "clip_29": {
            "is_summarization_sample": false,
            "summarization_data": [
                {
                    "sent": "Ask.",
                    "label": 0
                }
            ]
        },
        "clip_30": {
            "is_summarization_sample": false,
            "summarization_data": [
                {
                    "sent": "So.",
                    "label": 0
                }
            ]
        },
        "clip_31": {
            "is_summarization_sample": false,
            "summarization_data": [
                {
                    "sent": "Mute.",
                    "label": 0
                },
                {
                    "sent": "Now.",
                    "label": 0
                },
                {
                    "sent": "So.",
                    "label": 0
                },
                {
                    "sent": "We will send you value that essentially is a set of assets.",
                    "label": 0
                }
            ]
        },
        "clip_32": {
            "is_summarization_sample": false,
            "summarization_data": [
                {
                    "sent": "Anyway.",
                    "label": 0
                }
            ]
        },
        "clip_33": {
            "is_summarization_sample": false,
            "summarization_data": [
                {
                    "sent": "Is mean.",
                    "label": 0
                },
                {
                    "sent": "English.",
                    "label": 0
                },
                {
                    "sent": "We refresh.",
                    "label": 0
                },
                {
                    "sent": "Is the number of words that generated.",
                    "label": 0
                },
                {
                    "sent": "Anyway, the same number of words as in the original document in English.",
                    "label": 0
                },
                {
                    "sent": "Yelp?",
                    "label": 0
                },
                {
                    "sent": "French.",
                    "label": 0
                },
                {
                    "sent": "English in any way similar.",
                    "label": 0
                }
            ]
        },
        "clip_34": {
            "is_summarization_sample": false,
            "summarization_data": [
                {
                    "sent": "So.",
                    "label": 0
                },
                {
                    "sent": "Ratio.",
                    "label": 0
                },
                {
                    "sent": "As functional.",
                    "label": 0
                },
                {
                    "sent": "Value.",
                    "label": 0
                },
                {
                    "sent": "We have 2.5.",
                    "label": 0
                },
                {
                    "sent": "We generate new bag of Word document.",
                    "label": 0
                },
                {
                    "sent": "Document for particular query.",
                    "label": 0
                },
                {
                    "sent": "An ideal selection.",
                    "label": 0
                },
                {
                    "sent": "Write down the horizontal line when we're generating the exact number of words as well.",
                    "label": 0
                },
                {
                    "sent": "Is not that far.",
                    "label": 0
                },
                {
                    "sent": "Now obviously this query which so we do this for all the documents for French law.",
                    "label": 0
                }
            ]
        },
        "clip_35": {
            "is_summarization_sample": false,
            "summarization_data": [
                {
                    "sent": "Average across.",
                    "label": 0
                },
                {
                    "sent": "Automatic processing uses a space.",
                    "label": 0
                },
                {
                    "sent": "Cambridge.",
                    "label": 0
                },
                {
                    "sent": "Average.",
                    "label": 0
                },
                {
                    "sent": "Same number.",
                    "label": 0
                },
                {
                    "sent": "What was?",
                    "label": 0
                },
                {
                    "sent": "Unknown spots approach.",
                    "label": 0
                },
                {
                    "sent": "Getting massive we're happy with our processing.",
                    "label": 0
                },
                {
                    "sent": "Hollywood.",
                    "label": 0
                },
                {
                    "sent": "OK, so.",
                    "label": 0
                },
                {
                    "sent": "We go back to Maine.",
                    "label": 0
                },
                {
                    "sent": "One hour.",
                    "label": 0
                }
            ]
        },
        "clip_36": {
            "is_summarization_sample": false,
            "summarization_data": [
                {
                    "sent": "So I don't apologize.",
                    "label": 0
                },
                {
                    "sent": "So this is the French English schools discover header using 50 documents to train 250 for testing.",
                    "label": 0
                },
                {
                    "sent": "The X axis is the number of projection from use.",
                    "label": 0
                },
                {
                    "sent": "Point average.",
                    "label": 0
                },
                {
                    "sent": "The error summary.",
                    "label": 0
                },
                {
                    "sent": "So as we can see.",
                    "label": 0
                },
                {
                    "sent": "Obviously there is increasing.",
                    "label": 0
                },
                {
                    "sent": "And all.",
                    "label": 0
                },
                {
                    "sent": "Most of the time.",
                    "label": 0
                },
                {
                    "sent": "Sea is able to be spotted.",
                    "label": 0
                },
                {
                    "sent": "Conversions.",
                    "label": 0
                },
                {
                    "sent": "Here we use an increase another training document 200 test document.",
                    "label": 0
                },
                {
                    "sent": "One of them.",
                    "label": 0
                }
            ]
        },
        "clip_37": {
            "is_summarization_sample": false,
            "summarization_data": [
                {
                    "sent": "These two off for the 5th training with $50.",
                    "label": 0
                },
                {
                    "sent": "This is the one I was using.",
                    "label": 0
                },
                {
                    "sent": "OK, So what woman find that in this particular problem with 2007?",
                    "label": 0
                },
                {
                    "sent": "Over 140 bucks.",
                    "label": 0
                },
                {
                    "sent": "Which is interesting.",
                    "label": 0
                },
                {
                    "sent": "So really I go back.",
                    "label": 0
                },
                {
                    "sent": "Which.",
                    "label": 0
                },
                {
                    "sent": "Now here, so this is the primal weights.",
                    "label": 0
                },
                {
                    "sent": "And here's the deal work so.",
                    "label": 0
                },
                {
                    "sent": "Directions.",
                    "label": 0
                },
                {
                    "sent": "Projection.",
                    "label": 0
                },
                {
                    "sent": "On top of that.",
                    "label": 0
                },
                {
                    "sent": "24 documents OK.",
                    "label": 0
                }
            ]
        },
        "clip_38": {
            "is_summarization_sample": false,
            "summarization_data": [
                {
                    "sent": "Fashion increase.",
                    "label": 0
                },
                {
                    "sent": "The noise.",
                    "label": 0
                },
                {
                    "sent": "So.",
                    "label": 0
                },
                {
                    "sent": "How 100 documents with rating as 900 for testing.",
                    "label": 0
                },
                {
                    "sent": "The blue line in this case is today, the red line is pretty much.",
                    "label": 0
                },
                {
                    "sent": "Well.",
                    "label": 0
                }
            ]
        },
        "clip_39": {
            "is_summarization_sample": false,
            "summarization_data": [
                {
                    "sent": "Honda Fit.",
                    "label": 0
                },
                {
                    "sent": "Documents.",
                    "label": 0
                },
                {
                    "sent": "So.",
                    "label": 0
                },
                {
                    "sent": "OK, so.",
                    "label": 0
                },
                {
                    "sent": "The conclusion so.",
                    "label": 0
                }
            ]
        },
        "clip_40": {
            "is_summarization_sample": false,
            "summarization_data": [
                {
                    "sent": "We had a method which was.",
                    "label": 0
                },
                {
                    "sent": "On one view.",
                    "label": 0
                },
                {
                    "sent": "Images.",
                    "label": 0
                },
                {
                    "sent": "Then you can.",
                    "label": 0
                },
                {
                    "sent": "Then what's going on?",
                    "label": 0
                },
                {
                    "sent": "Generally.",
                    "label": 0
                },
                {
                    "sent": "Automatic.",
                    "label": 0
                },
                {
                    "sent": "Anne.",
                    "label": 0
                },
                {
                    "sent": "Exactly.",
                    "label": 0
                },
                {
                    "sent": "How to set?",
                    "label": 0
                },
                {
                    "sent": "We quote.",
                    "label": 0
                },
                {
                    "sent": "Project.",
                    "label": 0
                },
                {
                    "sent": "Projection.",
                    "label": 0
                },
                {
                    "sent": "Maybe you put protection.",
                    "label": 0
                },
                {
                    "sent": "Changes.",
                    "label": 0
                },
                {
                    "sent": "Negative.",
                    "label": 0
                },
                {
                    "sent": "How?",
                    "label": 0
                }
            ]
        },
        "clip_41": {
            "is_summarization_sample": false,
            "summarization_data": [
                {
                    "sent": "Population.",
                    "label": 0
                },
                {
                    "sent": "The problem with.",
                    "label": 0
                },
                {
                    "sent": "So far it's exactly algorithm.",
                    "label": 0
                },
                {
                    "sent": "Posted in conditional situations.",
                    "label": 0
                },
                {
                    "sent": "So in essence, I guess.",
                    "label": 0
                },
                {
                    "sent": "Modulation of the last Sue is equivalent to simply say that when you're estimating the application is not standard.",
                    "label": 0
                },
                {
                    "sent": "Problem here if you just add, just add.",
                    "label": 0
                },
                {
                    "sent": "So.",
                    "label": 0
                },
                {
                    "sent": "I have a question.",
                    "label": 0
                },
                {
                    "sent": "Never ever go back.",
                    "label": 0
                }
            ]
        },
        "clip_42": {
            "is_summarization_sample": false,
            "summarization_data": [
                {
                    "sent": "Old.",
                    "label": 0
                },
                {
                    "sent": "In this case.",
                    "label": 0
                },
                {
                    "sent": "Free.",
                    "label": 0
                },
                {
                    "sent": "Basically as well that we may have.",
                    "label": 0
                },
                {
                    "sent": "There is.",
                    "label": 0
                },
                {
                    "sent": "The problem is a magician with certain pressure because of his pain, which is somewhere and well so.",
                    "label": 0
                },
                {
                    "sent": "I'm not trying.",
                    "label": 0
                },
                {
                    "sent": "One, and then you guys.",
                    "label": 0
                },
                {
                    "sent": "Problem.",
                    "label": 0
                },
                {
                    "sent": "Starting point.",
                    "label": 0
                },
                {
                    "sent": "But I agree.",
                    "label": 0
                },
                {
                    "sent": "Penis",
                    "label": 0
                }
            ]
        }
    }
}